semvergit/__init__.py
semvergit/__main__.py
semvergit/app.py
semvergit/cli.py
semvergit/file_utils.py
semvergit/git_utils.py
semvergit/log_utils.py
semvergit-0.4.2.dist-info/LICENSE
semvergit-0.4.2.dist-info/METADATA
semvergit-0.4.2.dist-info/WHEEL
semvergit-0.4.2.dist-info/entry_points.txt
semvergit-0.4.2.dist-info/top_level.txt
semvergit-0.4.2.dist-info/RECORD
