Metadata-Version: 2.1
Name: semvergit
Version: 0.4.2
Summary: Manage your project's version numbers.
Author-email: Roy Moore <roy@moore.co.il>
Project-URL: homepage, https://github.com/Tranquility2/semvergit
Project-URL: repository, https://github.com/Tranquility2/semvergit
Keywords: packaging,publishing,release,versioning
Classifier: Development Status :: 4 - Beta
Classifier: Intended Audience :: Developers
Classifier: License :: OSI Approved :: MIT License
Classifier: Natural Language :: English
Classifier: Programming Language :: Python :: 3.8
Classifier: Programming Language :: Python :: 3.9
Classifier: Programming Language :: Python :: 3.10
Classifier: Programming Language :: Python :: 3.11
Classifier: Programming Language :: Python :: 3.12
Requires-Python: >=3.8
License-File: LICENSE
Requires-Dist: gitpython >=3.0.0
Requires-Dist: semver >=3.0.0
Requires-Dist: loguru >=0.7.0
Requires-Dist: click >=8.0.0
Provides-Extra: dev
Requires-Dist: astroid ==3.1.0 ; extra == 'dev'
Requires-Dist: bandit ==1.7.8 ; extra == 'dev'
Requires-Dist: black ==24.4.0 ; extra == 'dev'
Requires-Dist: cfgv ==3.4.0 ; extra == 'dev'
Requires-Dist: click ==8.1.7 ; extra == 'dev'
Requires-Dist: dill ==0.3.8 ; extra == 'dev'
Requires-Dist: distlib ==0.3.8 ; extra == 'dev'
Requires-Dist: filelock ==3.13.3 ; extra == 'dev'
Requires-Dist: identify ==2.5.35 ; extra == 'dev'
Requires-Dist: isort ==5.13.2 ; extra == 'dev'
Requires-Dist: markdown-it-py ==3.0.0 ; extra == 'dev'
Requires-Dist: mccabe ==0.7.0 ; extra == 'dev'
Requires-Dist: mdurl ==0.1.2 ; extra == 'dev'
Requires-Dist: mypy ==1.9.0 ; extra == 'dev'
Requires-Dist: mypy-extensions ==1.0.0 ; extra == 'dev'
Requires-Dist: nodeenv ==1.8.0 ; extra == 'dev'
Requires-Dist: packaging ==24.0 ; extra == 'dev'
Requires-Dist: pathspec ==0.12.1 ; extra == 'dev'
Requires-Dist: pbr ==6.0.0 ; extra == 'dev'
Requires-Dist: platformdirs ==4.2.0 ; extra == 'dev'
Requires-Dist: pre-commit ==3.5.0 ; extra == 'dev'
Requires-Dist: pygments ==2.17.2 ; extra == 'dev'
Requires-Dist: pylint ==3.1.0 ; extra == 'dev'
Requires-Dist: pyyaml ==6.0.1 ; extra == 'dev'
Requires-Dist: rich ==13.7.1 ; extra == 'dev'
Requires-Dist: stevedore ==5.2.0 ; extra == 'dev'
Requires-Dist: tomli ==2.0.1 ; extra == 'dev'
Requires-Dist: tomlkit ==0.12.4 ; extra == 'dev'
Requires-Dist: typing-extensions ==4.10.0 ; extra == 'dev'
Requires-Dist: virtualenv ==20.25.1 ; extra == 'dev'
Provides-Extra: test
Requires-Dist: coverage ==7.4.4 ; extra == 'test'
Requires-Dist: exceptiongroup ==1.2.0 ; extra == 'test'
Requires-Dist: iniconfig ==2.0.0 ; extra == 'test'
Requires-Dist: packaging ==24.0 ; extra == 'test'
Requires-Dist: pluggy ==1.4.0 ; extra == 'test'
Requires-Dist: pytest ==8.1.1 ; extra == 'test'
Requires-Dist: pytest-cov ==5.0.0 ; extra == 'test'
Requires-Dist: tomli ==2.0.1 ; extra == 'test'
